seg_mask_modifs/__init__.py
seg_mask_modifs/download_models.py
seg_mask_modifs/mask_generator.py
seg_mask_modifs/mask_modifier.py
seg_mask_modifs/mask_utils.py
seg_mask_modifs/print_labels.py
seg_mask_modifs/model_utils/__init__.py
seg_mask_modifs/model_utils/labels.py
seg_mask_modifs/model_utils/model_celebmask.py
seg_mask_modifs/model_utils/resnet.py
seg_mask_modifs-1.2.0.dist-info/LICENSE
seg_mask_modifs-1.2.0.dist-info/METADATA
seg_mask_modifs-1.2.0.dist-info/WHEEL
seg_mask_modifs-1.2.0.dist-info/top_level.txt
seg_mask_modifs-1.2.0.dist-info/RECORD
