Metadata-Version: 2.1
Name: seg-mask-modifs
Version: 1.2.0
Summary: A package for easy generation of mask of different labels using multiple models and applying different operations on that.
Home-page: https://github.com/vardanagarwal/seg_mask_modifs
Author: Vardan Agarwal
Author-email: vardanagarwal16@gmail.com
Project-URL: Bug Tracker, https://github.com/vardanagarwal/seg_mask_modifs/issues
Classifier: Programming Language :: Python :: 3
Classifier: License :: OSI Approved :: MIT License
Classifier: Operating System :: OS Independent
Requires-Python: >=3.6
License-File: LICENSE
Requires-Dist: torch (>=1.10.1)
Requires-Dist: torchvision (>=0.11.2)
Requires-Dist: numpy (>=1.21.4)
Requires-Dist: googledrivedownloader (>=0.4)
Requires-Dist: Pillow (>9.0.0)
